{
    "email_table": [
        {"column_name": "From", "type": "text"},
        {"column_name": "UID", "type": "text"},
        {"column_name": "Message ID", "type": "text"},
        {"column_name": "To", "type": "text"},
        {"column_name": "Subject", "type": "text"},
        {"column_name": "cc", "type": "text"},
        {"column_name": "Content", "type": "long-text"},
        {"column_name": "Date", "type": "date", "data": {"format": "YYYY-MM-DD"}},
        {"column_name": "Reply to Message ID", "type": "text"},
        {"column_name": "Thread ID", "type": "text"}
    ],
    "link_table": [
        {"column_name": "Subject", "type": "text"},
        {"column_name": "Last Updated", "type": "date", "data": {"format": "YYYY-MM-DD"}},
        {"column_name": "Thread ID", "type": "text"}
    ]
}
